oqpy/__init__.py
oqpy/base.py
oqpy/classical_types.py
oqpy/control_flow.py
oqpy/program.py
oqpy/pulse.py
oqpy/quantum_types.py
oqpy/subroutines.py
oqpy/timing.py
oqpy-0.3.9.dist-info/LICENSE
oqpy-0.3.9.dist-info/METADATA
oqpy-0.3.9.dist-info/NOTICE
oqpy-0.3.9.dist-info/WHEEL
oqpy-0.3.9.dist-info/RECORD
