Metadata-Version: 2.3
Name: oqpy
Version: 0.3.9
Summary: Generating OpenQASM 3 + OpenPulse in Python
License: Apache-2.0
Keywords: openqasm,quantum
Author: OQpy Contributors
Author-email: oqpy-contributors@amazon.com
Requires-Python: >=3.8,<4.0
Classifier: Intended Audience :: Developers
Classifier: Intended Audience :: Science/Research
Classifier: License :: OSI Approved :: Apache Software License
Classifier: Programming Language :: Python :: 3
Classifier: Programming Language :: Python :: 3.8
Classifier: Programming Language :: Python :: 3.9
Classifier: Programming Language :: Python :: 3.10
Classifier: Programming Language :: Python :: 3.11
Classifier: Programming Language :: Python :: 3.12
Classifier: Programming Language :: Python :: 3.13
Classifier: Topic :: Scientific/Engineering
Requires-Dist: mypy-extensions (>=0.2.0)
Requires-Dist: numpy (>=1.17.3) ; python_version == "3.8"
Requires-Dist: numpy (>=1.19.3) ; python_version == "3.9"
Requires-Dist: numpy (>=1.21.6) ; python_version == "3.10"
Requires-Dist: numpy (>=1.22.0) ; python_version >= "3.11"
Requires-Dist: openpulse (>=0.5.0)
Project-URL: Repository, https://github.com/openqasm/oqpy
